pydisseqt-0.2.0.dist-info/METADATA
pydisseqt-0.2.0.dist-info/WHEEL
pydisseqt-0.2.0.dist-info/licenses/LICENSE
pydisseqt/__init__.py
pydisseqt/__init__.pyi
pydisseqt/py.typed
pydisseqt/pydisseqt.cpython-311-arm-linux-gnueabihf.so
pydisseqt-0.2.0.dist-info/RECORD
